configure.py
setup.py
PyConfigure.egg-info/PKG-INFO
PyConfigure.egg-info/SOURCES.txt
PyConfigure.egg-info/dependency_links.txt
PyConfigure.egg-info/not-zip-safe
PyConfigure.egg-info/requires.txt
PyConfigure.egg-info/top_level.txt