Metadata-Version: 1.0
Name: PyConfigure
Version: 0.5.4
Summary: configuration toolkit based on YAML
Home-page: https://github.com/alfred82santa/configure
Author: Andrey Popp
Author-email: 8mayday@gmail.com
License: UNKNOWN
Platform: UNKNOWN
